zonis/__init__.py
zonis/client.py
zonis/exceptions.py
zonis/packet.py
zonis/server.py
zonisss-0.0.1.dist-info/LICENSE
zonisss-0.0.1.dist-info/METADATA
zonisss-0.0.1.dist-info/WHEEL
zonisss-0.0.1.dist-info/top_level.txt
zonisss-0.0.1.dist-info/RECORD
