Metadata-Version: 2.1
Name: zonisss
Version: 0.0.1
Author: skelmis
Author-email: ethan@koldfusion.xyz
License: MIT
Classifier: Programming Language :: Python :: 3
Classifier: License :: OSI Approved :: MIT License
Classifier: Operating System :: OS Independent
License-File: LICENSE
